.hgignore
BUGS
CHANGELOG
HACKING
LICENSE
README.txt
mkfile.py
setup.cfg
setup.py
mkcode/__init__.py
mkcode/collector.py
mkcode/console.py
mkcode/pathing.py
mkcode/registry.py
mkcode/resolver.py
mkcode.egg-info/PKG-INFO
mkcode.egg-info/SOURCES.txt
mkcode.egg-info/dependency_links.txt
mkcode.egg-info/entry_points.txt
mkcode.egg-info/top_level.txt
tests/__init__.py
tests/test_collection.py
tests/test_regressions.py
tests/test_resolver.py
tests/test_tasks.py
tests/trivialmkfile.py
