Metadata-Version: 1.0
Name: mkcode
Version: 0.2
Summary: A make-style Python build tool
Home-page: UNKNOWN
Author: Maris Fogels
Author-email: mfogels@gmail.com
License: MIT License
Platform: UNKNOWN
Classifier: Development Status :: 3 - Alpha
Classifier: Intended Audience :: Developers
Classifier: Topic :: Software Development :: Build Tools
Classifier: License :: OSI Approved :: MIT License
Classifier: Environment :: Console
